{"options":{"check_for_updates":true,"comment":null,"compat_foreach":false,"compat_metadata":false,"compat_powerful_this":null,"compat_wrappedjsobject":false,"compatopts_for_requires":true,"noframes":null,"override":{"merge_connects":true,"merge_excludes":true,"merge_includes":true,"merge_matches":true,"orig_connects":[],"orig_excludes":[],"orig_includes":[],"orig_matches":["*://*/*","*://medium.com/*","*://*.medium.com/*","https://freedium.cfd/*","https://readmedium.com/*","https://medium.rest/*","https://archive.is/*","https://archive.li/*","https://archive.vn/*","https://archive.ph/*","https://archive.fo/*","https://archive.md/*"],"orig_noframes":true,"orig_run_at":"document-idle","orig_run_in":[],"orig_tags":[],"use_blockers":[],"use_connects":[],"use_excludes":[],"use_includes":[],"use_matches":[]},"run_at":null,"run_in":null,"sandbox":null,"tags":[],"unwrap":null,"user_modified":null},"settings":{"enabled":true,"position":46},"meta":{"name":"Medium Member Bypass","uuid":"cc9987a3-10bd-4e8c-a12d-75f69d17656c","modified":1744119994103,"file_url":"https://update.greasyfork.org/scripts/520904/Medium%20Member%20Bypass.user.js"}}